pythologist_image_utilities/__init__.py
pythologist_image_utilities-1.0.2.dist-info/LICENSE
pythologist_image_utilities-1.0.2.dist-info/METADATA
pythologist_image_utilities-1.0.2.dist-info/WHEEL
pythologist_image_utilities-1.0.2.dist-info/top_level.txt
pythologist_image_utilities-1.0.2.dist-info/RECORD
