Metadata-Version: 2.1
Name: pythologist-image-utilities
Version: 1.0.2
Summary: Functions to assist in working with image files
Home-page: https://github.com/jason-weirather/pythologist-image-utilities
Author: Jason L Weirather
Author-email: jason.weirather@gmail.com
License: Apache License, Version 2.0
Keywords: bioinformatics
Platform: UNKNOWN
Classifier: Development Status :: 3 - Alpha
Classifier: Intended Audience :: Science/Research
Classifier: Topic :: Scientific/Engineering :: Bio-Informatics
Classifier: License :: OSI Approved :: Apache Software License
Requires-Dist: pandas (>=0.23.0)
Requires-Dist: numpy
Requires-Dist: scikit-image
Requires-Dist: scipy
